<?xml version="1.0" encoding="UTF-8"?>
<RtxMessage>    <Dec>
        <DecHead>
            <bgd_no>222920250002635501</bgd_no>
            <hgdjc_no></hgdjc_no>
            <Hxd_no></Hxd_no>
            <lj_date>20250721</lj_date>
            <ht_no>ATS25010</ht_no>
            <cj_type>CIF</cj_type>
            <yf>2450</yf>
            <yf_type>3</yf_type>
            <Yf_bz>USD</Yf_bz>
            <bf>20</bf>
            <Bf_type>3</Bf_type>
            <Bf_bz>USD</Bf_bz>
            <zf>0</zf>
            <Zf_type></Zf_type>
            <Zf_bz></Zf_bz>
            <my_type>0110</my_type>
            <traf_name>EVER ENVOY</traf_name>
        </DecHead>
        <DecLists>            <DecList>
                <spxh>1</spxh>
                <cmcode>2922499990</cmcode>
                <cm_name>氨基酸鳌合镁</cm_name>
                <Yb_bz>AUD</Yb_bz>
                <yb_amt>3000</yb_amt>
                <Fd_unit>035</Fd_unit>
                <Fd_qnt>200</Fd_qnt>
                <No2_Fd_unit></No2_Fd_unit>
                <No2_Fd_qnt>0</No2_Fd_qnt>
                <Cj_unit>035</Cj_unit>
                <Cj_qnt>200</Cj_qnt>
            </DecList>
                        <DecList>
                <spxh>2</spxh>
                <cmcode>2914620000</cmcode>
                <cm_name>辅酶Q10</cm_name>
                <Yb_bz>AUD</Yb_bz>
                <yb_amt>192000</yb_amt>
                <Fd_unit>035</Fd_unit>
                <Fd_qnt>800</Fd_qnt>
                <No2_Fd_unit></No2_Fd_unit>
                <No2_Fd_qnt>0</No2_Fd_qnt>
                <Cj_unit>035</Cj_unit>
                <Cj_qnt>800</Cj_qnt>
            </DecList>
                        <DecList>
                <spxh>3</spxh>
                <cmcode>2924199090</cmcode>
                <cm_name>L-瓜氨酸</cm_name>
                <Yb_bz>AUD</Yb_bz>
                <yb_amt>40000</yb_amt>
                <Fd_unit>035</Fd_unit>
                <Fd_qnt>4000</Fd_qnt>
                <No2_Fd_unit></No2_Fd_unit>
                <No2_Fd_qnt>0</No2_Fd_qnt>
                <Cj_unit>035</Cj_unit>
                <Cj_qnt>4000</Cj_qnt>
            </DecList>
                        <DecList>
                <spxh>4</spxh>
                <cmcode>2924199090</cmcode>
                <cm_name>L-瓜氨酸 DL-苹果酸</cm_name>
                <Yb_bz>AUD</Yb_bz>
                <yb_amt>27200</yb_amt>
                <Fd_unit>035</Fd_unit>
                <Fd_qnt>3200</Fd_qnt>
                <No2_Fd_unit></No2_Fd_unit>
                <No2_Fd_qnt>0</No2_Fd_qnt>
                <Cj_unit>035</Cj_unit>
                <Cj_qnt>3200</Cj_qnt>
            </DecList>
                        <DecList>
                <spxh>5</spxh>
                <cmcode>2923100000</cmcode>
                <cm_name>甘油磷酰胆碱</cm_name>
                <Yb_bz>AUD</Yb_bz>
                <yb_amt>18000</yb_amt>
                <Fd_unit>035</Fd_unit>
                <Fd_qnt>180</Fd_qnt>
                <No2_Fd_unit></No2_Fd_unit>
                <No2_Fd_qnt>0</No2_Fd_qnt>
                <Cj_unit>035</Cj_unit>
                <Cj_qnt>180</Cj_qnt>
            </DecList>
                        <DecList>
                <spxh>6</spxh>
                <cmcode>2925290090</cmcode>
                <cm_name>硫酸胍基丁胺</cm_name>
                <Yb_bz>AUD</Yb_bz>
                <yb_amt>11250</yb_amt>
                <Fd_unit>035</Fd_unit>
                <Fd_qnt>900</Fd_qnt>
                <No2_Fd_unit></No2_Fd_unit>
                <No2_Fd_qnt>0</No2_Fd_qnt>
                <Cj_unit>035</Cj_unit>
                <Cj_qnt>900</Cj_qnt>
            </DecList>
                        <DecList>
                <spxh>7</spxh>
                <cmcode>2938909090</cmcode>
                <cm_name>辛弗林盐酸盐</cm_name>
                <Yb_bz>AUD</Yb_bz>
                <yb_amt>14000</yb_amt>
                <Fd_unit>035</Fd_unit>
                <Fd_qnt>100</Fd_qnt>
                <No2_Fd_unit></No2_Fd_unit>
                <No2_Fd_qnt>0</No2_Fd_qnt>
                <Cj_unit>035</Cj_unit>
                <Cj_qnt>100</Cj_qnt>
            </DecList>
                        <DecList>
                <spxh>8</spxh>
                <cmcode>2923900090</cmcode>
                <cm_name>乙酰左旋肉碱盐酸盐</cm_name>
                <Yb_bz>AUD</Yb_bz>
                <yb_amt>94500</yb_amt>
                <Fd_unit>035</Fd_unit>
                <Fd_qnt>2700</Fd_qnt>
                <No2_Fd_unit></No2_Fd_unit>
                <No2_Fd_qnt>0</No2_Fd_qnt>
                <Cj_unit>035</Cj_unit>
                <Cj_qnt>2700</Cj_qnt>
            </DecList>
                    </DecLists>
    </Dec>
    </RtxMessage>

